odoo/addons/l10n_th_hr_employee_identification_id/README.rst
odoo/addons/l10n_th_hr_employee_identification_id/__init__.py
odoo/addons/l10n_th_hr_employee_identification_id/__manifest__.py
odoo/addons/l10n_th_hr_employee_identification_id/i18n/l10n_th_hr_employee_identification_id.pot
odoo/addons/l10n_th_hr_employee_identification_id/models/__init__.py
odoo/addons/l10n_th_hr_employee_identification_id/models/hr_employee.py
odoo/addons/l10n_th_hr_employee_identification_id/readme/CONTRIBUTORS.rst
odoo/addons/l10n_th_hr_employee_identification_id/readme/DESCRIPTION.rst
odoo/addons/l10n_th_hr_employee_identification_id/static/description/icon.png
odoo/addons/l10n_th_hr_employee_identification_id/static/description/index.html
odoo/addons/l10n_th_hr_employee_identification_id/tests/__init__.py
odoo/addons/l10n_th_hr_employee_identification_id/tests/test_hr_employee_id_validation.py
odoo13_addon_l10n_th_hr_employee_identification_id-13.0.1.0.1.dev3.dist-info/METADATA
odoo13_addon_l10n_th_hr_employee_identification_id-13.0.1.0.1.dev3.dist-info/WHEEL
odoo13_addon_l10n_th_hr_employee_identification_id-13.0.1.0.1.dev3.dist-info/top_level.txt
odoo13_addon_l10n_th_hr_employee_identification_id-13.0.1.0.1.dev3.dist-info/RECORD
